simple_photo_organizer/__init__.py
simple_photo_organizer/cli.py
simple_photo_organizer/utils/__init__.py
simple_photo_organizer/utils/helper_functions.py
simple_photo_organizer-0.1.3.1.dist-info/LICENSE
simple_photo_organizer-0.1.3.1.dist-info/METADATA
simple_photo_organizer-0.1.3.1.dist-info/WHEEL
simple_photo_organizer-0.1.3.1.dist-info/entry_points.txt
simple_photo_organizer-0.1.3.1.dist-info/top_level.txt
simple_photo_organizer-0.1.3.1.dist-info/RECORD
