Metadata-Version: 2.1
Name: simple-photo-organizer
Version: 0.1.3.1
Summary: A CLI tool for sorting photos into folders according to their modification date and numbering them. Needs exiftool to work and asks for permission to install it, if it is not found.
Home-page: https://github.com/Quaesius/Simple-Photo-Organizer
Author: Quaesius
License: UNKNOWN
Platform: UNKNOWN
Classifier: Programming Language :: Python :: 3
Classifier: License :: OSI Approved :: MIT License
Classifier: Operating System :: OS Independent
Requires-Python: >=3.6
License-File: LICENSE
Requires-Dist: Click
Requires-Dist: PyExifTool
